NeuroPixelAI/GUI.py
NeuroPixelAI/GUI.ui
NeuroPixelAI/__init__.py
NeuroPixelAI/__main__.py
NeuroPixelAI/denoisemodule.py
NeuroPixelAI/denoisemodule_srdtrans.py
NeuroPixelAI/regismodule.py
NeuroPixelAI/segmodule.py
NeuroPixelAI/str_version.py
NeuroPixelAI/test.py
NeuroPixelAI/Cascade/README.md
NeuroPixelAI/Cascade/__init__.py
NeuroPixelAI/Cascade/setup.py
NeuroPixelAI/Cascade/Demo_scripts/Calibrated_spike_inference_with_Cascade.ipynb
NeuroPixelAI/Cascade/Demo_scripts/Demo_benchmark_model.py
NeuroPixelAI/Cascade/Demo_scripts/Demo_discrete_spikes.py
NeuroPixelAI/Cascade/Demo_scripts/Demo_discrete_spikes_test.py
NeuroPixelAI/Cascade/Demo_scripts/Demo_predict.ipynb
NeuroPixelAI/Cascade/Demo_scripts/Demo_predict.py
NeuroPixelAI/Cascade/Demo_scripts/Demo_train.ipynb
NeuroPixelAI/Cascade/Demo_scripts/Demo_train.py
NeuroPixelAI/Cascade/Demo_scripts/Explore_ground_truth_datasets.ipynb
NeuroPixelAI/Cascade/Demo_scripts/__pycache__/Demo_predict.cpython-37.pyc
NeuroPixelAI/Cascade/Demo_scripts/__pycache__/Demo_predict.cpython-38.pyc
NeuroPixelAI/Cascade/Pretrained_models/0.98Hz_1500ms_causal_kernal/Model_NoiseLevel_2_Ensemble_0.h5
NeuroPixelAI/Cascade/Pretrained_models/0.98Hz_1500ms_causal_kernal/Model_NoiseLevel_2_Ensemble_1.h5
NeuroPixelAI/Cascade/Pretrained_models/0.98Hz_1500ms_causal_kernal/Model_NoiseLevel_2_Ensemble_2.h5
NeuroPixelAI/Cascade/Pretrained_models/0.98Hz_1500ms_causal_kernal/Model_NoiseLevel_2_Ensemble_3.h5
NeuroPixelAI/Cascade/Pretrained_models/0.98Hz_1500ms_causal_kernal/Model_NoiseLevel_2_Ensemble_4.h5
NeuroPixelAI/Cascade/Pretrained_models/0.98Hz_1500ms_causal_kernal/Model_NoiseLevel_3_Ensemble_0.h5
NeuroPixelAI/Cascade/Pretrained_models/0.98Hz_1500ms_causal_kernal/Model_NoiseLevel_3_Ensemble_1.h5
NeuroPixelAI/Cascade/Pretrained_models/0.98Hz_1500ms_causal_kernal/Model_NoiseLevel_3_Ensemble_2.h5
NeuroPixelAI/Cascade/Pretrained_models/0.98Hz_1500ms_causal_kernal/Model_NoiseLevel_3_Ensemble_3.h5
neuroai-0.5.2.dist-info/LICENSE
neuroai-0.5.2.dist-info/METADATA
neuroai-0.5.2.dist-info/WHEEL
neuroai-0.5.2.dist-info/top_level.txt
neuroai-0.5.2.dist-info/RECORD
