Metadata-Version: 2.1
Name: neuroai
Version: 0.5.2
Summary: A package for calcium image processing
Home-page: 
Author: HuJiahao
Author-email: dadadadasukede@gmail.com
Classifier: Programming Language :: Python :: 3
Classifier: License :: OSI Approved :: GNU General Public License v3 (GPLv3)
Classifier: Operating System :: Microsoft :: Windows
Requires-Python: >=3.8
License-File: LICENSE
Requires-Dist: datetime ==5.4
Requires-Dist: tqdm ==4.66.2
Requires-Dist: fastremap ==1.14.1
Requires-Dist: scikit-learn ==1.2.2
Requires-Dist: numpy ==1.18.5
Requires-Dist: scipy ==1.4.1
Requires-Dist: torch
Requires-Dist: tifffile
Requires-Dist: paramiko ==3.4.0
Requires-Dist: pillow ==9.1
Requires-Dist: PyQt5
Requires-Dist: pyqt5-sip ==12.12.2
Requires-Dist: scikit-image ==0.17.2
Requires-Dist: opencv-python ==4.9.0.80
Requires-Dist: pyqtgraph ==0.12.4
Requires-Dist: ruamel.yaml ==0.18.6
Requires-Dist: tensorflow ==2.3.0
Requires-Dist: keras ==2.3.1
Requires-Dist: natsort ==8.4.0
Requires-Dist: numba ==0.56.4
Requires-Dist: matplotlib ==3.5.0
Requires-Dist: protobuf ==3.20.1
Requires-Dist: csaps ==1.1.0
Requires-Dist: einops
Requires-Dist: timm ==0.5.4
